osmlf/__init__.py
osmlf/main.py
osmlf/overpass_calculations.py
osmlf/overpass_operations.py
osmlf/overpass_queries.py
osmlf-0.0.1.dist-info/LICENSE
osmlf-0.0.1.dist-info/METADATA
osmlf-0.0.1.dist-info/WHEEL
osmlf-0.0.1.dist-info/top_level.txt
osmlf-0.0.1.dist-info/RECORD
