Metadata-Version: 2.1
Name: osmlf
Version: 0.0.1
Summary: Retrieve given location features using OpenStreetMap
Home-page: https://github.com/ccan23/osmlf
Author: ccan23
Author-email: dev.ccanb@protonmail.com
License: MIT
Keywords: python,map,openstreetmap,amenities,location,coordinates,latitude,longitude
Platform: UNKNOWN
Classifier: Development Status :: 3 - Alpha
Classifier: Intended Audience :: Developers
Classifier: Programming Language :: Python :: 3
Classifier: Operating System :: OS Independent
Classifier: License :: OSI Approved :: MIT License
License-File: LICENSE
Requires-Dist: certifi (==2023.5.7)
Requires-Dist: charset-normalizer (==3.2.0)
Requires-Dist: geographiclib (==2.0)
Requires-Dist: geopy (==2.3.0)
Requires-Dist: idna (==3.4)
Requires-Dist: numpy (==1.25.0)
Requires-Dist: overpy (==0.6)
Requires-Dist: pyproj (==3.6.0)
Requires-Dist: requests (==2.31.0)
Requires-Dist: shapely (==2.0.1)
Requires-Dist: urllib3 (==2.0.4)
